django_habitat/__init__.py
django_habitat/exceptions.py
django_habitat/templates.py
django_habitat/core/__init__.py
django_habitat/core/environments.py
django_habitat/management/__init__.py
django_habitat/management/commands/__init__.py
django_habitat/management/commands/create-habitat.py
django_habitat/management/commands/start-habitat.py
django_habitat/management/commands/switch-habitat.py
django_habitat-0.3.0a2.dist-info/DESCRIPTION.rst
django_habitat-0.3.0a2.dist-info/METADATA
django_habitat-0.3.0a2.dist-info/RECORD
django_habitat-0.3.0a2.dist-info/WHEEL
django_habitat-0.3.0a2.dist-info/metadata.json
django_habitat-0.3.0a2.dist-info/top_level.txt
tests/__init__.py
tests/test_create_habitat.py
tests/test_start_habitat.py
tests/test_switch_habitat.py
tests/support/__init__.py
tests/support/setup_installed_apps.py
