Metadata-Version: 2.0
Name: django-habitat
Version: 0.3.0a2
Summary: A powerful and smarter environment manager for django projects
Home-page: https://github.com/regisec/django-habitat/
Author: Régis Eduardo Crestani
Author-email: regis.crestani@gmail.com
License: BSD
Platform: UNKNOWN
Classifier: Development Status :: 3 - Alpha
Classifier: Intended Audience :: Developers
Classifier: Framework :: Django
Classifier: Topic :: Software Development
Classifier: License :: OSI Approved :: BSD License
Classifier: Programming Language :: Python
Classifier: Programming Language :: Python :: 2
Classifier: Programming Language :: Python :: 3
